{
  "last_update": "2026-03-06T03:05:00.011632",
  "stats": {
    "timestamp": "2026-03-06T02:52:56.230193",
    "days_back": 7,
    "sources": {
      "cna": {
        "scraped": 43,
        "status": "success"
      },
      "xinhua": {
        "scraped": 9,
        "status": "success"
      },
      "weibo": {
        "scraped": 16,
        "status": "success"
      }
    },
    "deduplication": {
      "before": 68,
      "after": 52,
      "removed": 16
    },
    "classification": {
      "total": 52,
      "relevant": 34,
      "status": "success"
    },
    "naval_transits": {
      "new_entries": 2,
      "status": "success"
    }
  }
}