[
  {
    "publish_date": "2026-03-16",
    "title": "BOHAI SEA MILITARY EXERCISES—LN94/26",
    "channel": "辽宁海事局",
    "time_periods": "",
    "coordinate_count": 3,
    "coordinates": "40.3555,120.5755; 40.3705,120.6083; 40.1922,120.5308",
    "coordinates_raw": "40-21.33N 120-34.53E; 40-22.23N 120-36.5E; 40-11.53N 120-31.85E",
    "content_preview": "English x 中国海事公众号 海事通App 首页 机构职能 机构职责 领导介绍 内设机构 直属单位 政府信息公开 法定主动公开内容 政府信息公开指南 政府信息公开制度 政府信息公开年报 依申请公开 互联网+政务 我要办事 在线查询 航行安全 AIS信息服务 安全信息 北极航道 安全知识 潮汐查询 搜救辅助 海图改正通告 海图服务 事故教训 海事履约 互动交流 在线访谈 网上咨询 政策法规解读 意见征集·在线调查 局长信箱 投诉举报 海事数据 首页 航行安全 安全信息 航行警告 辽宁海事局 BOHAI SEA MILITARY EXERCISES—LN94/26 来源：葫芦岛海事局 文号：LN94/26 发布时间：2026-03-16 16:08 [字体： 大 中 小 ] 分享到： LN94/26 BOHAI SEA MILITARY EXERCISES IN AREA BOUNDED BY THE LINES JOINING40-21.33N 120-34.53E，40-22.23N 120-36.5E，40-11.53N 120-31.85E AND 40-11.88N 120",
    "url": "https://www.msa.gov.cn/page/article.do?articleId=b3c826ea8acba5ef&channelId=C8896863-B101-4C43-8705-536A03EB46FF",
    "scraped_at": "2026-03-17T04:26:08.505093"
  },
  {
    "publish_date": "2026-03-16",
    "title": "渤海军事演习—辽航警104/26",
    "channel": "辽宁海事局",
    "time_periods": "17日0500时至0900时; 自3月17日0500时至0900时",
    "coordinate_count": 4,
    "coordinates": "40.3555,120.5755; 40.3705,120.6083; 40.1922,120.5308; 40.198,120.507",
    "coordinates_raw": "40-21.33N 120-34.53E; 40-22.23N 120-36.5E; 40-11.53N 120-31.85E; 40-11.88N 120-30.42E",
    "content_preview": "辽航警104/26，渤海，自3月17日0500时至0900时在40-21.33N 120-34.53E、40-22.23N 120-36.5E、40-11.53N 120-31.85E和40-11.88N 120-30.42E诸点连线范围内进行军事演习。禁止驶入。",
    "url": "https://www.msa.gov.cn/page/article.do?articleId=1e8ecfc5-b066-4e2b-a06c-d45886f1272a&channelId=C8896863-B101-4C43-8705-536A03EB46FF",
    "scraped_at": "2026-03-17T04:26:10.680100"
  },
  {
    "publish_date": "2026-03-13",
    "title": "MILITARY MISSION—LN91/26",
    "channel": "辽宁海事局",
    "time_periods": "",
    "coordinate_count": 3,
    "coordinates": "38.8617,121.6367; 38.57,121.6367; 38.565,121.1317",
    "coordinates_raw": "38-51.7N121-38.2E; 38-34.2N121-38.2E; 38-33.9N121-07.9E",
    "content_preview": "English x 中国海事公众号 海事通App 首页 机构职能 机构职责 领导介绍 内设机构 直属单位 政府信息公开 法定主动公开内容 政府信息公开指南 政府信息公开制度 政府信息公开年报 依申请公开 互联网+政务 我要办事 在线查询 航行安全 AIS信息服务 安全信息 北极航道 安全知识 潮汐查询 搜救辅助 海图改正通告 海图服务 事故教训 海事履约 互动交流 在线访谈 网上咨询 政策法规解读 意见征集·在线调查 局长信箱 投诉举报 海事数据 首页 航行安全 安全信息 航行警告 辽宁海事局 MILITARY MISSION—LN91/26 来源：大连海事局 文号：LN91/26 发布时间：2026-03-13 11:49 [字体： 大 中 小 ] 分享到： LN91/26 BOHAI STRAIT AND NORTH YELLOW SEA MILITARY MISSION IN AREA BOUNDED BY THE LINES JOINING 38-51.7N121-38.2E,38-34.2N121-38.2E,38-33.9N121-07.9E,38-48.2N121-14.",
    "url": "https://www.msa.gov.cn/page/article.do?articleId=2a416a790560fd51&channelId=C8896863-B101-4C43-8705-536A03EB46FF",
    "scraped_at": "2026-03-17T04:26:12.826053"
  },
  {
    "publish_date": "2026-03-13",
    "title": "军事任务—辽航警101/26",
    "channel": "辽宁海事局",
    "time_periods": "自3月15日1600时至29日1600时",
    "coordinate_count": 4,
    "coordinates": "38.8617,121.6367; 38.57,121.6367; 38.565,121.1317; 38.8033,121.235",
    "coordinates_raw": "38-51.7N121-38.2E; 38-34.2N121-38.2E; 38-33.9N121-07.9E; 38-48.2N121-14.1E",
    "content_preview": "辽航警101/26，渤海海峡黄海北部，自3月15日1600时至29日1600时在38-51.7N121-38.2E、38-34.2N121-38.2E、38-33.9N121-07.9E、38-48.2N121-14.1E诸点连线范围内执行军事任务。禁止驶入。",
    "url": "https://www.msa.gov.cn/page/article.do?articleId=1e2047d9-b7cb-4507-8109-484d0231b4c3&channelId=C8896863-B101-4C43-8705-536A03EB46FF",
    "scraped_at": "2026-03-17T04:26:14.909551"
  },
  {
    "publish_date": "2026-03-15",
    "title": "军事训练—桂航警51/26",
    "channel": "广西海事局",
    "time_periods": "",
    "coordinate_count": 4,
    "coordinates": "21.3833,108.79; 21.3833,108.9667; 21.2067,108.9667; 21.2067,108.79",
    "coordinates_raw": "21-23.00N 108-47.40E; 21-23.00N 108-58.00E; 21-12.40N 108-58.00E; 21-12.40N 108-47.40E",
    "content_preview": "桂航警51/26 发布时间：2026-03-15 13:35 [字体： 大 中 小 ] 分享到： 桂航警51/26，北部湾，3月16日至17日每天1000时至1800时，在21-23.00N 108-47.40E；21-23.00N 108-58.00E；21-12.40N 108-58.00E；21-12.40N 108-47.40E连线海域范围内进行军事训练，禁止船舶驶入。",
    "url": "https://www.msa.gov.cn/page/article.do?articleId=935a9173-17d9-441f-b69d-3b5bd7896713&channelId=86DE2FFF-FF2C-47F9-8359-FD1F20D6508F",
    "scraped_at": "2026-03-17T04:26:33.749877"
  },
  {
    "publish_date": "2026-03-15",
    "title": "MILITARY TRAINING—GX20/26",
    "channel": "广西海事局",
    "time_periods": "",
    "coordinate_count": 4,
    "coordinates": "21.3833,108.79; 21.3833,108.9667; 21.2067,108.9667; 21.2067,108.79",
    "coordinates_raw": "21-23.00N 108-47.40E; 21-23.00N 108-58.00E; 21-12.40N 108-58.00E; 21-12.40N 108-47.40E",
    "content_preview": "GX20/26 BEIBU BAY，MILITARY TRAINING IN AREA BOUNDED BY THE LINES JOINING 21-23.00N 108-47.40E；21-23.00N 108-58.00E；21-12.40N 108-58.00E；21-12.40N 108-47.40E 0200 UTC TO 1000 UTC DAILY FROM 16 TO 17 MAR. ENTERING PROHIBITED．GUANGXI MSA CHINA.",
    "url": "https://www.msa.gov.cn/page/article.do?articleId=d836fc484471b449&channelId=86DE2FFF-FF2C-47F9-8359-FD1F20D6508F",
    "scraped_at": "2026-03-17T04:26:35.839847"
  },
  {
    "publish_date": "2026-03-11",
    "title": "火箭发射—琼航警25/26",
    "channel": "海南海事局",
    "time_periods": "自3月13日至3月14日，每日0250时至0450时",
    "coordinate_count": 1,
    "coordinates": "19.6,110.93",
    "coordinates_raw": "19-36.00N 110-55.80E",
    "content_preview": "琼航警25/26 发布时间：2026-03-11 18:00 [字体： 大 中 小 ] 分享到： 琼航警25/26，南海，自3月13日至3月14日，每日0250时至0450时，在以19-36.00N 110-55.80E为中心，6海里为半径的圆形区域内进行火箭发射，禁止驶入。",
    "url": "https://www.msa.gov.cn/page/article.do?articleId=072aed58-2988-4c3e-8897-2672e65e7780&channelId=D3340711-057B-494B-8FA0-9EEDC4C5EAD9",
    "scraped_at": "2026-03-17T04:26:40.455285"
  },
  {
    "publish_date": "2026-03-11",
    "title": "火箭残骸掉落—琼航警24/26",
    "channel": "海南海事局",
    "time_periods": "2026年3月13日0050时至0650时; 13日0050时至0650时; 3月13日0050时至0650时",
    "coordinate_count": 4,
    "coordinates": "12.32,116.58; 13.18,115.9; 13.52,116.34; 12.66,117.03",
    "coordinates_raw": "12-19.20N 116-34.80E; 13-10.80N 115-54.00E; 13-31.20N 116-20.40E; 12-39.60N 117-01.80E",
    "content_preview": "琼航警24/26 发布时间：2026-03-11 16:05 [字体： 大 中 小 ] 分享到： 琼航警24/26，南海，自2026年3月13日0050时至0650时，在12-19.20N 116-34.80E、13-10.80N 115-54.00E、13-31.20N 116-20.40E、12-39.60N 117-01.80E诸点连线水域范围内有火箭残骸掉落，禁止驶入。",
    "url": "https://www.msa.gov.cn/page/article.do?articleId=70a5e595-43f7-4a75-9141-f2a1d14b20cf&channelId=D3340711-057B-494B-8FA0-9EEDC4C5EAD9",
    "scraped_at": "2026-03-17T04:26:42.537739"
  },
  {
    "publish_date": "2026-02-09",
    "title": "军事行动—琼航警19/26",
    "channel": "海南海事局",
    "time_periods": "自2月11日至12日，每日0700时至1330时",
    "coordinate_count": 4,
    "coordinates": "19.6782,111.2115; 19.3863,111.2765; 19.3202,110.9802; 19.6118,110.915",
    "coordinates_raw": "19-40.69N 111-12.69E; 19-23.18N 111-16.59E; 19-19.21N 110-58.81E; 19-36.71N 110-54.9E",
    "content_preview": "琼航警19/26 发布时间：2026-02-09 21:51 [字体： 大 中 小 ] 分享到： 琼航警19/26，南海，自2月11日至12日，每日0700时至1330时，在以19-40.69N 111-12.69E、19-23.18N 111-16.59E、19-19.21N 110-58.81E、19-36.71N 110-54.9E四点连线水域范围内进行军事行动，禁止驶入。",
    "url": "https://www.msa.gov.cn/page/article.do?articleId=f3130dd7-0a08-4894-bf59-d164dadf0f3e&channelId=D3340711-057B-494B-8FA0-9EEDC4C5EAD9",
    "scraped_at": "2026-03-17T04:26:44.652940"
  },
  {
    "publish_date": "2026-02-09",
    "title": "MILITARY OPERATION—HN17/26",
    "channel": "海南海事局",
    "time_periods": "",
    "coordinate_count": 3,
    "coordinates": "19.6782,111.2115; 19.3863,111.2765; 19.3202,110.9802",
    "coordinates_raw": "19-40.69N 111-12.69E; 19-23.18N 111-16.59E; 19-19.21N 110-58.81E",
    "content_preview": "English x 中国海事公众号 海事通App 首页 机构职能 机构职责 领导介绍 内设机构 直属单位 政府信息公开 法定主动公开内容 政府信息公开指南 政府信息公开制度 政府信息公开年报 依申请公开 互联网+政务 我要办事 在线查询 航行安全 AIS信息服务 安全信息 北极航道 安全知识 潮汐查询 搜救辅助 海图改正通告 海图服务 事故教训 海事履约 互动交流 在线访谈 网上咨询 政策法规解读 意见征集·在线调查 局长信箱 投诉举报 海事数据 首页 航行安全 安全信息 航行警告 海南海事局 MILITARY OPERATION—HN17/26 来源：清澜海事局 文号：HN17/26 发布时间：2026-02-09 21:51 [字体： 大 中 小 ] 分享到： HN17/26 SOUTH CHINA SEA . MILITARY OPERATION IN AREA BOUNDED BY THE LINES JOINING 19-40.69N 111-12.69E、19-23.18N 111-16.59E、19-19.21N 110-58.81E、19-36.71N 110-54.9",
    "url": "https://www.msa.gov.cn/page/article.do?articleId=26c80f80518cffd4&channelId=D3340711-057B-494B-8FA0-9EEDC4C5EAD9",
    "scraped_at": "2026-03-17T04:26:46.838145"
  }
]